LICENSE
MANIFEST.in
README.md
requirements.txt
setup.cfg
setup.py
switchcache/__init__.py
switchcache/test.py
switchcache.egg-info/PKG-INFO
switchcache.egg-info/SOURCES.txt
switchcache.egg-info/dependency_links.txt
switchcache.egg-info/requires.txt
switchcache.egg-info/top_level.txt