Metadata-Version: 1.1
Name: switchcache
Version: 0.1.1
Summary: Utils for testing with/without cache
Home-page: http://github.com/shoz/switchcache
Author: Shoji Ihara
Author-email: shoji.ihara@gmail.com
License: switchcache
